{
  "fetched_at": "2026-04-16T10:44:42.860069+00:00",
  "count": 206,
  "articles": [
    {
      "id": "028d3154e2",
      "title": "Nicola Coughlan and Lydia West on Messiness, Mental Health and That Iconic Celebrity Guest Star in ‘Big Mood’ Season 2: “It Was a Dream”",
      "link": "https://www.hollywoodreporter.com/tv/tv-features/nicola-coughlan-lydia-west-big-mood-season-2-interview-show-1236561049/",
      "pubDate": "Thu, 16 Apr 2026 10:30:00 +0000",
      "source": "THR TV",
      "sourceId": "thr_tv",
      "tab": "news"
    },
    {
      "id": "b1c5314e27",
      "title": "Gugu Mbatha-Raw Leading BBC Sci-Fi Series About Space Travel",
      "link": "https://deadline.com/2026/04/gugu-mbatha-raw-bbc-sci-fi-series-sutherland-1236862876/",
      "pubDate": "Thu, 16 Apr 2026 10:16:38 +0000",
      "source": "Deadline TV",
      "sourceId": "deadline_tv",
      "tab": "news"
    },
    {
      "id": "4bdadbe72d",
      "title": "Krise und kein Ende: Der ORF steht vor einem Scherbenhaufen",
      "link": "https://www.dwdl.de/magazin/106191/krise_und_kein_ende_der_orf_steht_vor_einem_scherbenhaufen/",
      "pubDate": "Thu, 16 Apr 2026 12:15:00 +0200",
      "source": "DWDL",
      "sourceId": "dwdl_all",
      "tab": "german"
    },
    {
      "id": "97a8406238",
      "title": "Cannes’ Directors’ Fortnight Movie ‘La Perra’ From ‘I’m Still Here’ Producer Boarded by Lucky Number (EXCLUSIVE)",
      "link": "https://variety.com/2026/film/global/cannes-directors-fortnight-la-perra-lucky-number-1236723311/",
      "pubDate": "Thu, 16 Apr 2026 09:57:25 +0000",
      "source": "Variety",
      "sourceId": "variety_film",
      "tab": "news"
    },
    {
      "id": "7c32bb47a6",
      "title": "Podcast mit Mai und Weippert, das \"Sandmädchen\" kommt",
      "link": "https://www.dwdl.de/audioupdate/106190/podcast_mit_mai_und_weippert_das_sandmaedchen_kommt/",
      "pubDate": "Thu, 16 Apr 2026 11:47:00 +0200",
      "source": "DWDL",
      "sourceId": "dwdl_all",
      "tab": "german"
    },
    {
      "id": "82de050d2d",
      "title": "Channel 4 Chief Content Officer Ian Katz Stepping Down After 9 Years",
      "link": "https://variety.com/2026/tv/global/channel-4-chief-content-officer-ian-katz-stepping-down-1236723333/",
      "pubDate": "Thu, 16 Apr 2026 09:44:42 +0000",
      "source": "Variety TV",
      "sourceId": "variety_tv",
      "tab": "news"
    },
    {
      "id": "2d9b63f775",
      "title": "Channel 4’s Chief Content Officer Ian Katz To Exit After Nine Years",
      "link": "https://deadline.com/2026/04/channel-4-chief-content-ian-katz-to-exit-1236862846/",
      "pubDate": "Thu, 16 Apr 2026 09:35:09 +0000",
      "source": "Deadline TV",
      "sourceId": "deadline_tv",
      "tab": "news"
    },
    {
      "id": "5a358386d0",
      "title": "YMU Signs Presenter & Podcaster Vogue Williams",
      "link": "https://deadline.com/2026/04/ymu-signs-vogue-williams-1236862849/",
      "pubDate": "Thu, 16 Apr 2026 09:30:00 +0000",
      "source": "Deadline TV",
      "sourceId": "deadline_tv",
      "tab": "news"
    },
    {
      "id": "92ec181404",
      "title": "How major and indie cinema chains are using AI tools: “They are saving me at least one day a week”",
      "link": "https://www.screendaily.com/features/how-major-and-indie-cinema-chains-are-using-ai-tools-they-are-saving-me-at-least-one-day-a-week/5215694.article",
      "pubDate": "Thu, 16 Apr 2026 09:17:00 GMT",
      "source": "Screen Daily",
      "sourceId": "screen_main",
      "tab": "industry"
    },
    {
      "id": "af7cf4f84e",
      "title": "Marvel, DC and ‘Planet of the Apes’ Actor Kirk Acevedo Had to Sell His Home Because ‘Middle Class’ Actors Are Getting ‘Squeezed Out’ of Hollywood",
      "link": "https://variety.com/2026/tv/news/kirk-acevedo-sold-house-middle-class-actors-hollywood-1236722809/",
      "pubDate": "Thu, 16 Apr 2026 09:00:07 +0000",
      "source": "Variety",
      "sourceId": "variety_film",
      "tab": "news"
    },
    {
      "id": "e5c0ecffcb",
      "title": "‘Spring Wind – The Awakening’ Doc, Charting Rise of Hungary’s Election Winner Péter Magyar, Set to Open Italy’s Riviera Film Festival",
      "link": "https://variety.com/2026/film/global/hungarian-leader-peter-magyar-documentary-open-riviera-festival-1236723281/",
      "pubDate": "Thu, 16 Apr 2026 08:54:43 +0000",
      "source": "Variety",
      "sourceId": "variety_film",
      "tab": "news"
    },
    {
      "id": "3496975fbe",
      "title": "Amol Rajan To Deliver Edinburgh TV Fest Alternative MacTaggart",
      "link": "https://deadline.com/2026/04/amol-rajan-edinburgh-alternative-mactaggart-vicky-mcclure-1236862829/",
      "pubDate": "Thu, 16 Apr 2026 08:30:00 +0000",
      "source": "Deadline TV",
      "sourceId": "deadline_tv",
      "tab": "news"
    },
    {
      "id": "49af7227f4",
      "title": "Adelaide Film Festival Goes to Cannes Lineup Includes Ukrainian War Portrait, Ecuador Indigenous Doc and Victorian Wilderness Thriller (EXCLUSIVE)",
      "link": "https://variety.com/2026/film/markets-festivals/adelaide-film-festival-goes-to-cannes-2026-lineup-1236723195/",
      "pubDate": "Thu, 16 Apr 2026 08:00:00 +0000",
      "source": "Variety",
      "sourceId": "variety_film",
      "tab": "news"
    },
    {
      "id": "4f85c85cf8",
      "title": "Channel 5’s Rags-To-Riches Series ‘The Hardacres’ Unveils New Cast & First Look At Season 2",
      "link": "https://deadline.com/2026/04/channel-5-the-hardacres-season-2-cast-first-look-1236861326/",
      "pubDate": "Thu, 16 Apr 2026 08:00:00 +0000",
      "source": "Deadline TV",
      "sourceId": "deadline_tv",
      "tab": "news"
    },
    {
      "id": "1ca47dd297",
      "title": "Joyn+ führt Download-Funktion ein und wird teurer",
      "link": "https://www.dwdl.de/nachrichten/106184/joyn_fuehrt_downloadfunktion_ein_und_wird_teurer/",
      "pubDate": "Thu, 16 Apr 2026 10:00:00 +0200",
      "source": "DWDL",
      "sourceId": "dwdl_all",
      "tab": "german"
    },
    {
      "id": "32a15b5dee",
      "title": "Erfolgreicher Start für \"Kampf der RealityAllstars\" bei RTLzwei",
      "link": "https://www.dwdl.de/zahlenzentrale/106189/erfolgreicher_start_fuer_kampf_der_realityallstars_bei_rtlzwei/",
      "pubDate": "Thu, 16 Apr 2026 09:39:00 +0200",
      "source": "DWDL",
      "sourceId": "dwdl_all",
      "tab": "german"
    },
    {
      "id": "e8f2402c12",
      "title": "CL bei DAZN: Schon die linearen Zahlen sind ein Mega-Erfolg",
      "link": "https://www.dwdl.de/zahlenzentrale/106188/cl_bei_dazn_schon_die_linearen_zahlen_sind_ein_megaerfolg/",
      "pubDate": "Thu, 16 Apr 2026 09:21:00 +0200",
      "source": "DWDL",
      "sourceId": "dwdl_all",
      "tab": "german"
    },
    {
      "id": "364e33e47f",
      "title": "Amazon MGM Studios teases ‘Highlander’, ‘The Thomas Crown Affair’ at CinemaCon – but no James Bond",
      "link": "https://www.screendaily.com/news/amazon-mgm-studios-teases-highlander-the-thomas-crown-affair-at-cinemacon-but-no-james-bond/5215711.article",
      "pubDate": "Thu, 16 Apr 2026 07:11:00 GMT",
      "source": "Screen Daily",
      "sourceId": "screen_main",
      "tab": "industry"
    },
    {
      "id": "d488657e88",
      "title": "All The Songs In Netflix’s ‘Beef’ Across Both Seasons",
      "link": "https://deadline.com/lists/songs-in-beef-both-seasons/",
      "pubDate": "Thu, 16 Apr 2026 07:05:00 +0000",
      "source": "Deadline TV",
      "sourceId": "deadline_tv",
      "tab": "news"
    },
    {
      "id": "4b4726eb3c",
      "title": "‘Beef’ Is Overcrowded and Unfocused in an Unnecessary Season 2: TV Review",
      "link": "https://variety.com/2026/tv/reviews/beef-season-2-review-netflix-1236722589/",
      "pubDate": "Thu, 16 Apr 2026 07:01:00 +0000",
      "source": "Variety TV",
      "sourceId": "variety_tv",
      "tab": "news"
    },
    {
      "id": "4d92302692",
      "title": "‘Beef’ Review: Prime Performances by Oscar Isaac and Carey Mulligan Make for a Juicy Season 2 of Netflix’s Smash",
      "link": "https://www.hollywoodreporter.com/tv/tv-reviews/beef-season-2-review-oscar-isaac-carey-mulligan-netflix-1236565867/",
      "pubDate": "Thu, 16 Apr 2026 07:01:00 +0000",
      "source": "THR TV",
      "sourceId": "thr_tv",
      "tab": "news"
    },
    {
      "id": "ea058e4e3b",
      "title": "‘Beef’ Season 2 Review: Bigger Is Actually Better in Lee Sung Jin’s Searing Netflix Sequel",
      "link": "https://www.indiewire.com/criticism/shows/beef-season-2-review-netflix-series-1235188904/",
      "pubDate": "Thu, 16 Apr 2026 07:01:00 +0000",
      "source": "IndieWire TV",
      "sourceId": "indiewire_tv",
      "tab": "news"
    },
    {
      "id": "2b2164cfae",
      "title": "\"Inside\": RTL-Reihe knackt mit AIDA die 20-Prozent-Marke",
      "link": "https://www.dwdl.de/zahlenzentrale/106187/inside_rtlreihe_knackt_mit_aida_die_20prozentmarke/",
      "pubDate": "Thu, 16 Apr 2026 08:56:00 +0200",
      "source": "DWDL",
      "sourceId": "dwdl_all",
      "tab": "german"
    },
    {
      "id": "f56a8f789a",
      "title": "‘The Price of the Sun’ Director on How He Is Giving Viewers the Impression of “Being in the Desert With Nomads” Affected by Our Energy Consumption",
      "link": "https://www.hollywoodreporter.com/movies/movie-news/the-price-of-the-sun-doc-film-visions-du-reel-berber-solar-1236561749/",
      "pubDate": "Thu, 16 Apr 2026 06:00:00 +0000",
      "source": "THR",
      "sourceId": "thr_film",
      "tab": "news"
    },
    {
      "id": "52565a9d0f",
      "title": "Die Deutsche Telekom und ihr Überraschungsangriff in Österreich",
      "link": "https://www.dwdl.de/magazin/106180/die_deutsche_telekom_und_ihr_ueberraschungsangriff_in_oesterreich/",
      "pubDate": "Thu, 16 Apr 2026 08:00:00 +0200",
      "source": "DWDL",
      "sourceId": "dwdl_all",
      "tab": "german"
    },
    {
      "id": "02ee3dd447",
      "title": "‘I Play Rocky’ First Look Takes On Backstory Of The Iconic Film – CinemaCon",
      "link": "https://deadline.com/2026/04/i-play-rocky-peter-farrelly-amazon-mgm-cinemacon-1236862604/",
      "pubDate": "Thu, 16 Apr 2026 05:57:47 +0000",
      "source": "Deadline",
      "sourceId": "deadline_film",
      "tab": "news"
    },
    {
      "id": "62bff7e4cd",
      "title": "ProSiebenSat.1-Mutter MFE kann Gewinn mehr als verdoppeln",
      "link": "https://www.dwdl.de/nachrichten/106186/prosiebensat1mutter_mfe_kann_gewinn_mehr_als_verdoppeln/",
      "pubDate": "Thu, 16 Apr 2026 07:50:00 +0200",
      "source": "DWDL",
      "sourceId": "dwdl_all",
      "tab": "german"
    },
    {
      "id": "b26cf10375",
      "title": "Anthony Ippolito Comes to Life as Young Sylvester Stallone in First ‘I Play Rocky’ Footage",
      "link": "https://www.hollywoodreporter.com/movies/movie-news/anthony-ippolito-young-sylvester-stallone-i-play-rocky-1236565233/",
      "pubDate": "Thu, 16 Apr 2026 05:44:39 +0000",
      "source": "THR",
      "sourceId": "thr_film",
      "tab": "news"
    },
    {
      "id": "d4a23df9a0",
      "title": "Michael B. Jordan, Ryan Gosling, and Even Rick Moranis — But No James Bond — Lead Star-Studded Amazon MGM CinemaCon",
      "link": "https://www.indiewire.com/news/breaking-news/amazon-mgm-cinemacon-michael-b-jordan-rick-moranis-1235189428/",
      "pubDate": "Thu, 16 Apr 2026 05:31:08 +0000",
      "source": "IndieWire",
      "sourceId": "indiewire_film",
      "tab": "news"
    },
    {
      "id": "298ded6d7d",
      "title": "‘I Play Rocky’ CinemaCon Trailer: Newcomer Anthony Ippolito Is Dead Ringer for Sylvester Stallone",
      "link": "https://variety.com/2026/film/news/i-play-rocky-cinemacon-trailer-sylvester-stallone-1236722980/",
      "pubDate": "Thu, 16 Apr 2026 05:28:51 +0000",
      "source": "Variety",
      "sourceId": "variety_film",
      "tab": "news"
    },
    {
      "id": "1d7cdd563c",
      "title": "‘Highlander’ First Footage Unveils Henry Cavill’s ‘John Wick’-Esque Action, Rave Fight Scene and Immortal Killers",
      "link": "https://variety.com/2026/film/news/highlander-footage-henry-cavill-john-wick-reboot-1236712744/",
      "pubDate": "Thu, 16 Apr 2026 05:25:59 +0000",
      "source": "Variety",
      "sourceId": "variety_film",
      "tab": "news"
    },
    {
      "id": "a96de9a85a",
      "title": "Amazon MGM Studios Offers First Look At Henry Cavill In New ‘Highlander’ – CinemaCon",
      "link": "https://deadline.com/2026/04/highlander-henry-cavill-cinemacon-1236862582/",
      "pubDate": "Thu, 16 Apr 2026 05:23:54 +0000",
      "source": "Deadline",
      "sourceId": "deadline_film",
      "tab": "news"
    },
    {
      "id": "612518a861",
      "title": "Henry Cavill Unveils ‘Highlander’ Reboot’s Thrilling First Footage",
      "link": "https://www.hollywoodreporter.com/movies/movie-news/highlander-first-look-henry-cavill-reboot-chad-stahelski-1236565574/",
      "pubDate": "Thu, 16 Apr 2026 05:19:17 +0000",
      "source": "THR",
      "sourceId": "thr_film",
      "tab": "news"
    },
    {
      "id": "2b9c05db74",
      "title": "Nicholas Hoult Leads a Crew of Criminal YouTubers in First ‘How to Rob a Bank’ Footage",
      "link": "https://www.hollywoodreporter.com/movies/movie-news/nicholas-hoult-youtubers-how-to-rob-a-bank-1236565221/",
      "pubDate": "Thu, 16 Apr 2026 05:14:38 +0000",
      "source": "THR",
      "sourceId": "thr_film",
      "tab": "news"
    },
    {
      "id": "813ceabc5f",
      "title": "Anne Hathaway and Dakota Johnson Face Off in First ‘Verity’ Trailer",
      "link": "https://www.hollywoodreporter.com/movies/movie-news/anne-hathaway-dakota-johnson-verity-trailer-cinemacon-1236565203/",
      "pubDate": "Thu, 16 Apr 2026 05:04:57 +0000",
      "source": "THR",
      "sourceId": "thr_film",
      "tab": "news"
    },
    {
      "id": "83e350c4ff",
      "title": "Thriller ‘Verity’ First Look: Stepping Into The Writing Life Of Someone Else – CinemaCon",
      "link": "https://deadline.com/2026/04/verity-first-look-dakota-johnson-anne-hathaway-cinemacon-1236861441/",
      "pubDate": "Thu, 16 Apr 2026 05:03:22 +0000",
      "source": "Deadline",
      "sourceId": "deadline_film",
      "tab": "news"
    },
    {
      "id": "c5e5d296c9",
      "title": "‘Four Minus Three,’ Film About Family, Tears, Clowns and Hope That Won a Berlin Award, Sells to France, Canada, Australia",
      "link": "https://www.hollywoodreporter.com/movies/movie-news/four-minus-three-film-valerie-pachner-sales-france-canada-1236566050/",
      "pubDate": "Thu, 16 Apr 2026 05:00:00 +0000",
      "source": "THR",
      "sourceId": "thr_film",
      "tab": "news"
    },
    {
      "id": "6644d079e9",
      "title": "‘Spaceballs 2’ Trailer Spoofs ‘Star Wars’ Lightsaber Fights, ‘Avatar’ and Hollywood Mergers in Hilarious Sequel Titled ‘The New One’",
      "link": "https://variety.com/2026/film/news/spaceballs-2-trailer-star-wars-the-new-one-title-1236720900/",
      "pubDate": "Thu, 16 Apr 2026 04:52:40 +0000",
      "source": "Variety",
      "sourceId": "variety_film",
      "tab": "news"
    },
    {
      "id": "4d7be1ed12",
      "title": "‘How To Rob A Bank’ First Look: Nicholas Hoult Makes Heist-Themed Online Content In David Leitch Amazon Flick – CinemaCon",
      "link": "https://deadline.com/2026/04/how-to-rob-a-bank-david-leitch-pete-davidson-cinemacon-1236861439/",
      "pubDate": "Thu, 16 Apr 2026 04:46:45 +0000",
      "source": "Deadline",
      "sourceId": "deadline_film",
      "tab": "news"
    },
    {
      "id": "1edd73edf7",
      "title": "Mel Brooks Unveils Title to ‘Spaceballs’ Sequel",
      "link": "https://www.hollywoodreporter.com/movies/movie-news/spaceballs-sequel-title-the-new-one-1236566078/",
      "pubDate": "Thu, 16 Apr 2026 04:43:51 +0000",
      "source": "THR",
      "sourceId": "thr_film",
      "tab": "news"
    },
    {
      "id": "47edaa36ec",
      "title": "Mike Hopkins Says Amazon MGM Committed To Theatrical, Not “A Test Or An Experiment” – CinemaCon",
      "link": "https://deadline.com/2026/04/mike-hopkins-amazon-mgm-theatrical-cinemacon-1236862584/",
      "pubDate": "Thu, 16 Apr 2026 04:43:40 +0000",
      "source": "Deadline",
      "sourceId": "deadline_film",
      "tab": "news"
    },
    {
      "id": "42809feb08",
      "title": "James Bond Casting Process Teased by Amazon MGM: “A Responsibility We Don’t Take Lightly”",
      "link": "https://www.hollywoodreporter.com/movies/movie-news/james-bond-casting-denis-villeneuve-amazon-mgm-cinemacon-1236566187/",
      "pubDate": "Thu, 16 Apr 2026 04:37:52 +0000",
      "source": "THR",
      "sourceId": "thr_film",
      "tab": "news"
    },
    {
      "id": "84136793b1",
      "title": "‘Spaceballs 2’ Gets Official Title At CinemaCon; Rick Moranis Makes Appearance Alongside Co-Stars, Director Josh Greenbaum",
      "link": "https://deadline.com/2026/04/spaceballs-2-sets-title-cinemacon-1236861444/",
      "pubDate": "Thu, 16 Apr 2026 04:36:00 +0000",
      "source": "Deadline",
      "sourceId": "deadline_film",
      "tab": "news"
    },
    {
      "id": "bc544f8d1d",
      "title": "Jason Statham Unleashes ‘The Beekeeper 2’ Footage on CinemaCon",
      "link": "https://www.hollywoodreporter.com/movies/movie-news/the-beekeeper-2-footage-jason-statham-cinemacon-1236565700/",
      "pubDate": "Thu, 16 Apr 2026 04:30:45 +0000",
      "source": "THR",
      "sourceId": "thr_film",
      "tab": "news"
    },
    {
      "id": "b2dcd23f99",
      "title": "“All Hail the Queen”: Donna Langley’s Power on Full Display as Snoop Dogg, Christopher Nolan, Steven Spielberg Bet on Universal",
      "link": "https://www.hollywoodreporter.com/movies/movie-news/donna-langley-power-full-display-universal-cinemacon-2026-1236565953/",
      "pubDate": "Thu, 16 Apr 2026 04:27:42 +0000",
      "source": "THR",
      "sourceId": "thr_film",
      "tab": "news"
    },
    {
      "id": "11e9796064",
      "title": "Amazon MGM’s Search for New James Bond Actor: ‘We’re Taking the Time to Do This With Care and Deep Respect’",
      "link": "https://variety.com/2026/film/news/amazon-james-bond-actor-search-taking-time-1236722826/",
      "pubDate": "Thu, 16 Apr 2026 04:16:00 +0000",
      "source": "Variety",
      "sourceId": "variety_film",
      "tab": "news"
    },
    {
      "id": "6ac79a4de9",
      "title": "Amazon MGM’s Courtenay Valenti On James Bond: “That Film Is Coming … We’re Taking The Time To Do This With Care And Deep Respect” – CinemaCon",
      "link": "https://deadline.com/2026/04/amazon-mgm-courtenay-valenti-james-bond-film-coming-cinemacon-1236862658/",
      "pubDate": "Thu, 16 Apr 2026 04:12:56 +0000",
      "source": "Deadline",
      "sourceId": "deadline_film",
      "tab": "news"
    },
    {
      "id": "54286f64f3",
      "title": "CinemaCon 2026 Photos: Ryan Gosling, Michael B. Jordan, Camila Mendes & Nicholas Galitzine",
      "link": "https://deadline.com/gallery/cinemacon-2026-photos/",
      "pubDate": "Thu, 16 Apr 2026 04:10:00 +0000",
      "source": "Deadline",
      "sourceId": "deadline_film",
      "tab": "news"
    },
    {
      "id": "8351d75e5b",
      "title": "Amazon MGM Makes Blood Oath to Theater Owners of 15 Movies Per Year: ‘Project Hail Mary’ Was ‘Just the Beginning’",
      "link": "https://variety.com/2026/film/news/amazon-mgm-cinemacon-theaterical-movie-promise-1236723209/",
      "pubDate": "Thu, 16 Apr 2026 04:05:59 +0000",
      "source": "Variety",
      "sourceId": "variety_film",
      "tab": "news"
    },
    {
      "id": "496fd32727",
      "title": "Michael B. Jordan Shows Off ‘Thomas Crown Affair’ First Look, With Jon Batiste Revealed As Score Composer – CinemaCon",
      "link": "https://deadline.com/2026/04/thomas-crown-affair-michael-b-jordan-jon-batiste-cinemacon-1236861437/",
      "pubDate": "Thu, 16 Apr 2026 03:58:32 +0000",
      "source": "Deadline",
      "sourceId": "deadline_film",
      "tab": "news"
    },
    {
      "id": "9db7c1a0f0",
      "title": "‘The Thomas Crown Affair’ CinemaCon Tease: Michael B. Jordan Remakes a Classic",
      "link": "https://www.indiewire.com/news/breaking-news/michael-b-jordan-the-thomas-crown-affair-remake-cinemacon-1235188969/",
      "pubDate": "Thu, 16 Apr 2026 03:50:50 +0000",
      "source": "IndieWire",
      "sourceId": "indiewire_film",
      "tab": "news"
    },
    {
      "id": "9ef1dab5b8",
      "title": "Michael B. Jordan’s ‘Thomas Crown Affair’ Trailer Seduces CinemaCon With Art, Sex and an Oscar-Winning Six Pack",
      "link": "https://variety.com/2026/film/news/michael-b-jordan-thomas-crown-affair-trailer-sex-cinemacon-1236722975/",
      "pubDate": "Thu, 16 Apr 2026 03:49:40 +0000",
      "source": "Variety",
      "sourceId": "variety_film",
      "tab": "news"
    },
    {
      "id": "bc73e14ccd",
      "title": "Steven Spielberg rallies CinemaCon exhibitors: “If you ever need a bigger boat, I am that man”",
      "link": "https://www.screendaily.com/news/steven-spielberg-rallies-cinemacon-exhibitors-if-you-ever-need-a-bigger-boat-i-am-that-man/5215712.article",
      "pubDate": "Thu, 16 Apr 2026 02:16:00 GMT",
      "source": "Screen Daily",
      "sourceId": "screen_main",
      "tab": "industry"
    },
    {
      "id": "2a8ca794d0",
      "title": "Steven Spielberg Praises Universal For Commitment To 45-Day Window — “Do I Hear 60?” — In Appearance At His First CinemaCon With ‘Disclosure Day’",
      "link": "https://deadline.com/2026/04/steven-spielberg-cinemacon-appearance-disclosure-day-1236862313/",
      "pubDate": "Thu, 16 Apr 2026 02:02:09 +0000",
      "source": "Deadline",
      "sourceId": "deadline_film",
      "tab": "news"
    },
    {
      "id": "61c7b5210f",
      "title": "‘Disclosure Day’ New Footage: A Local TV Anchor Loses Her Voice On Air But Finds A New One – CinemaCon",
      "link": "https://deadline.com/2026/04/disclosure-day-steven-spielberg-cinemacon-1236861433/",
      "pubDate": "Thu, 16 Apr 2026 01:31:02 +0000",
      "source": "Deadline",
      "sourceId": "deadline_film",
      "tab": "news"
    },
    {
      "id": "62f3f6082e",
      "title": "Netflix Latin America’s Francisco Ramos Says: ‘I Believe It’s Crucial for Talented People to Feel They Can Succeed in Their Own Country’ (EXCLUSIVE)",
      "link": "https://variety.com/2026/film/global/francisco-ramos-netflix-one-hundred-years-of-solitude-1236721639/",
      "pubDate": "Thu, 16 Apr 2026 01:30:00 +0000",
      "source": "Variety TV",
      "sourceId": "variety_tv",
      "tab": "news"
    },
    {
      "id": "6036666eb2",
      "title": "Christopher Nolan Tells CinemaCon ‘The Odyssey’ Was a ‘Nightmare to Film…but in All the Right Ways’",
      "link": "https://www.indiewire.com/news/breaking-news/universal-cinemacon-day-3-the-odyssey-christopher-nolan-1235189226/",
      "pubDate": "Thu, 16 Apr 2026 01:09:56 +0000",
      "source": "IndieWire",
      "sourceId": "indiewire_film",
      "tab": "news"
    },
    {
      "id": "bc7a99d48a",
      "title": "‘Lorne’ Review: Just When You Thought You Were Done Looking Back at ‘SNL,’ Morgan Neville’s Puckishly Playful Lorne Michaels Doc Completes the Picture",
      "link": "https://variety.com/2026/film/reviews/lorne-review-lorne-michaels-saturday-night-live-1236721401/",
      "pubDate": "Thu, 16 Apr 2026 00:52:02 +0000",
      "source": "Variety TV",
      "sourceId": "variety_tv",
      "tab": "news"
    },
    {
      "id": "be93368575",
      "title": "Dave Chappelle Doesn’t Like His Trans Jokes Being “Weaponized” By GOP, Claims They Aren’t Meant To Be “Malicious”",
      "link": "https://deadline.com/2026/04/dave-chappelle-trans-jokes-weaponized-gop-1236862392/",
      "pubDate": "Thu, 16 Apr 2026 00:43:40 +0000",
      "source": "Deadline TV",
      "sourceId": "deadline_tv",
      "tab": "news"
    },
    {
      "id": "c3b3b020d1",
      "title": "‘Werwulf’ Trailer Unveiled As Focus Features Touts Robert Eggers’ “Most Terrifying Motion Picture Yet” – CinemaCon",
      "link": "https://deadline.com/2026/04/werwulf-first-look-robert-eggers-cinemacon-1236861425/",
      "pubDate": "Thu, 16 Apr 2026 00:41:05 +0000",
      "source": "Deadline",
      "sourceId": "deadline_film",
      "tab": "news"
    },
    {
      "id": "22060c185c",
      "title": "‘Focker In-Law’ Trailer: Ariana Grande Prepares to Meet the Parents",
      "link": "https://www.indiewire.com/news/trailers/focker-in-law-trailer-ariana-grande-1235189314/",
      "pubDate": "Thu, 16 Apr 2026 00:38:01 +0000",
      "source": "IndieWire",
      "sourceId": "indiewire_film",
      "tab": "news"
    },
    {
      "id": "6e017bea45",
      "title": "‘Lord of the Flies’ and ‘Spartacus: House of Ashur’ Screenings Among Programming Added to SeriesFest’s 2026 Lineup (EXCLUSIVE)",
      "link": "https://variety.com/2026/tv/news/lord-of-the-flies-spartacus-house-of-ashur-seriesfest-1236723049/",
      "pubDate": "Thu, 16 Apr 2026 00:35:13 +0000",
      "source": "Variety TV",
      "sourceId": "variety_tv",
      "tab": "news"
    },
    {
      "id": "95252ba44d",
      "title": "‘Werwulf’ Tease: Robert Eggers’ 13th-Century Horror Movie Haunts CinemaCon with First Footage",
      "link": "https://www.indiewire.com/news/breaking-news/werwulf-first-footage-cinemacon-1235189286/",
      "pubDate": "Thu, 16 Apr 2026 00:34:45 +0000",
      "source": "IndieWire",
      "sourceId": "indiewire_film",
      "tab": "news"
    },
    {
      "id": "aefc176cd4",
      "title": "‘Scrubs’ EP Aseem Batra On Dr. Cox’s Prognosis, Season 2 Bringing Back Beloved Feature & More OG Characters – Paging Dr. Kelso… And Dr. Murphy?",
      "link": "https://deadline.com/2026/04/scrubs-ep-aseem-batra-season-2-original-characters-1236858214/",
      "pubDate": "Thu, 16 Apr 2026 00:30:20 +0000",
      "source": "Deadline TV",
      "sourceId": "deadline_tv",
      "tab": "news"
    },
    {
      "id": "095593b071",
      "title": "‘Scrubs’ Showrunner Talks J.D. & Elliot’s Future & How Rachel Bilson Fits Into It, Reveals Cut Scene That Explains Interns’ Surprise Finale Pairings",
      "link": "https://deadline.com/2026/04/scrubs-showrunner-j-d-elliots-future-rachel-bilson-1236845685/",
      "pubDate": "Thu, 16 Apr 2026 00:30:00 +0000",
      "source": "Deadline TV",
      "sourceId": "deadline_tv",
      "tab": "news"
    },
    {
      "id": "21b7d21c07",
      "title": "‘Scrubs’ Season Finale Refuses to Tie Up Loose Ends",
      "link": "https://www.hollywoodreporter.com/tv/tv-features/scrubs-season-finale-season-2-possibility-1236565732/",
      "pubDate": "Thu, 16 Apr 2026 00:30:00 +0000",
      "source": "THR TV",
      "sourceId": "thr_tv",
      "tab": "news"
    },
    {
      "id": "d58b72c5fe",
      "title": "‘Baywatch’ Reboot: Erika Eleniak to Reprise Role of Shauni McClain",
      "link": "https://variety.com/2026/tv/news/baywatch-reboot-erika-eleniak-shauni-mcclain-1236723009/",
      "pubDate": "Thu, 16 Apr 2026 00:00:00 +0000",
      "source": "Variety TV",
      "sourceId": "variety_tv",
      "tab": "news"
    },
    {
      "id": "d2458b79e8",
      "title": "‘The World of the Married’ Director Mo Wan-il Sets Netflix K-Drama ‘The Facade of Love’ With Lee Dong-wook, Jeon So-nee, Jung Yu-mi",
      "link": "https://variety.com/2026/tv/news/world-of-the-married-director-netflix-facade-of-love-1236722326/",
      "pubDate": "Thu, 16 Apr 2026 00:00:00 +0000",
      "source": "Variety TV",
      "sourceId": "variety_tv",
      "tab": "news"
    },
    {
      "id": "b2c5a43abb",
      "title": "Erika Eleniak Set To Reprise ‘Baywatch’ Role Of Shauni McClain In Fox’s Sequel Series",
      "link": "https://deadline.com/2026/04/erika-eleniak-baywatch-shauni-mcclain-fox-1236862298/",
      "pubDate": "Thu, 16 Apr 2026 00:00:00 +0000",
      "source": "Deadline TV",
      "sourceId": "deadline_tv",
      "tab": "news"
    },
    {
      "id": "3aa08e48dd",
      "title": "Netflix Sets Korean Drama ‘The Facade of Love’ From ‘World of the Married’ Director Mo Wan-il",
      "link": "https://www.hollywoodreporter.com/tv/tv-news/netflix-korean-drama-the-facade-of-love-world-1236564955/",
      "pubDate": "Thu, 16 Apr 2026 00:00:00 +0000",
      "source": "THR TV",
      "sourceId": "thr_tv",
      "tab": "news"
    },
    {
      "id": "62b05d0535",
      "title": "‘The Odyssey’ Tease: Christopher Nolan Shows Off Epic Trojan Horse Sequence at CinemaCon",
      "link": "https://www.indiewire.com/news/breaking-news/the-odyssey-cinema-con-preview-trojan-horse-1235188867/",
      "pubDate": "Wed, 15 Apr 2026 23:47:53 +0000",
      "source": "IndieWire",
      "sourceId": "indiewire_film",
      "tab": "news"
    },
    {
      "id": "0775751c58",
      "title": "CBS Boss On Why Network Went With ‘NCIS: New York’ And Not ‘Tony & Ziva’ For Next Season",
      "link": "https://deadline.com/2026/04/cbs-ncis-new-york-ll-cool-j-tony-and-ziva-cancellation-1236862229/",
      "pubDate": "Wed, 15 Apr 2026 23:40:41 +0000",
      "source": "Deadline TV",
      "sourceId": "deadline_tv",
      "tab": "news"
    },
    {
      "id": "beced02773",
      "title": "‘The Copenhagen Test’ Canceled After One Season At Peacock",
      "link": "https://deadline.com/2026/04/the-copenhagen-test-canceled-one-season-peacock-simu-liu-1236862296/",
      "pubDate": "Wed, 15 Apr 2026 23:36:56 +0000",
      "source": "Deadline TV",
      "sourceId": "deadline_tv",
      "tab": "news"
    },
    {
      "id": "d1c64a0aad",
      "title": "Lili Reinhart Talks Harsh Realities of Indie TV Making and Having to “Shapeshift” a Show to Sell It",
      "link": "https://www.hollywoodreporter.com/tv/tv-features/lili-reinhart-hal-harper-indie-tv-filmmaking-interview-1236565913/",
      "pubDate": "Wed, 15 Apr 2026 23:32:16 +0000",
      "source": "THR TV",
      "sourceId": "thr_tv",
      "tab": "news"
    },
    {
      "id": "f6a689ff6f",
      "title": "‘Copenhagen Test’ Canceled After One Season at Peacock (EXCLUSIVE)",
      "link": "https://variety.com/2026/tv/news/copenhagen-test-canceled-simu-liu-1236722877/",
      "pubDate": "Wed, 15 Apr 2026 23:00:00 +0000",
      "source": "Variety TV",
      "sourceId": "variety_tv",
      "tab": "news"
    },
    {
      "id": "26deff7870",
      "title": "Kennedy Ryan Inks First-Look Deal at Universal Studio Group With ‘Before I Let Go’ Series in the Works at Peacock (EXCLUSIVE)",
      "link": "https://variety.com/2026/tv/news/kennedy-ryan-before-i-let-go-peacock-series-universal-first-look-deal-1236722727/",
      "pubDate": "Wed, 15 Apr 2026 22:46:07 +0000",
      "source": "Variety TV",
      "sourceId": "variety_tv",
      "tab": "news"
    },
    {
      "id": "feb0d852fe",
      "title": "‘The Testaments’ Creator Explains Biggest Change From the Book and Reveals Multi-Season Plan",
      "link": "https://www.hollywoodreporter.com/tv/tv-features/the-testaments-daisy-change-more-seasons-creator-interview-1236565411/",
      "pubDate": "Wed, 15 Apr 2026 22:00:00 +0000",
      "source": "THR TV",
      "sourceId": "thr_tv",
      "tab": "news"
    },
    {
      "id": "f73d3b344e",
      "title": "2026 Emmy Predictions: Who Will Win at the Primetime Emmy Awards?",
      "link": "https://www.indiewire.com/lists/2026-emmy-predictions-primetime-awards/",
      "pubDate": "Wed, 15 Apr 2026 22:00:00 +0000",
      "source": "IndieWire TV",
      "sourceId": "indiewire_tv",
      "tab": "news"
    },
    {
      "id": "9b5952a18a",
      "title": "The Drama Series Emmy Race Amounts to ‘The Pitt’ vs. ‘Pluribus,’ Surrounded by Plenty of HBO Shows",
      "link": "https://www.indiewire.com/awards/predictions/drama-series-emmy-race-the-pitt-pluribus-hbo-shows-1235189372/",
      "pubDate": "Wed, 15 Apr 2026 21:45:00 +0000",
      "source": "IndieWire TV",
      "sourceId": "indiewire_tv",
      "tab": "news"
    },
    {
      "id": "f28f2fe6e9",
      "title": "Adobe Premiere Just Made Color Correction Easier",
      "link": "https://www.indiewire.com/news/general-news/adobe-premiere-color-correction-premiere-davinci-resolve-1235189303/",
      "pubDate": "Wed, 15 Apr 2026 21:30:00 +0000",
      "source": "IndieWire",
      "sourceId": "indiewire_film",
      "tab": "news"
    },
    {
      "id": "c0d91c4745",
      "title": "The Surprisingly Lowkey Ending of ‘Smiling Friends’",
      "link": "https://www.indiewire.com/features/commentary/smiling-friends-ending-finale-adult-swim-1235189258/",
      "pubDate": "Wed, 15 Apr 2026 21:00:00 +0000",
      "source": "IndieWire TV",
      "sourceId": "indiewire_tv",
      "tab": "news"
    },
    {
      "id": "50587ab366",
      "title": "‘Beyond the Gates’ Renewed for Third and Fourth Seasons at CBS",
      "link": "https://www.hollywoodreporter.com/tv/tv-news/beyond-the-gates-renewed-through-season-4-cbs-1236565594/",
      "pubDate": "Wed, 15 Apr 2026 20:37:43 +0000",
      "source": "THR TV",
      "sourceId": "thr_tv",
      "tab": "news"
    },
    {
      "id": "083ff8ffff",
      "title": "Khloé Kardashian Responds to Lamar Odom’s Claims He Married Her For Fame, Feels “Played” for Participating in His Doc",
      "link": "https://www.hollywoodreporter.com/tv/tv-news/khloe-kardashian-reacts-lamar-odom-doc-marraige-fame-1236565404/",
      "pubDate": "Wed, 15 Apr 2026 20:07:48 +0000",
      "source": "THR TV",
      "sourceId": "thr_tv",
      "tab": "news"
    },
    {
      "id": "8a78a23d25",
      "title": "CBS 2026-27 Schedule: ‘Ghosts,’ ‘Matlock’ Move to Midseason, ‘Cupertino’ Legal Drama Gets Fall Spot",
      "link": "https://www.hollywoodreporter.com/tv/tv-news/cbs-2026-27-tv-schedule-1236565533/",
      "pubDate": "Wed, 15 Apr 2026 20:01:38 +0000",
      "source": "THR TV",
      "sourceId": "thr_tv",
      "tab": "news"
    },
    {
      "id": "3c17cbc6e6",
      "title": "‘NCIS’ Franchise Expands to New York, LL Cool J Returning as Sam Hanna",
      "link": "https://www.hollywoodreporter.com/tv/tv-news/ncis-new-york-ll-cool-j-scott-caan-1236565477/",
      "pubDate": "Wed, 15 Apr 2026 20:00:00 +0000",
      "source": "THR TV",
      "sourceId": "thr_tv",
      "tab": "news"
    },
    {
      "id": "d1c7f3d574",
      "title": "The Mind-Bending ‘Exit 8’ Turns the Subway Into Your Worst Nightmare — If It Wasn’t Already",
      "link": "https://www.indiewire.com/features/interviews/exit-8-movie-behind-the-scenes-interview-genki-kawamura-1235189210/",
      "pubDate": "Wed, 15 Apr 2026 20:00:00 +0000",
      "source": "IndieWire",
      "sourceId": "indiewire_film",
      "tab": "news"
    },
    {
      "id": "74bc169e1b",
      "title": "Hope Is Not a Distribution Strategy",
      "link": "https://www.indiewire.com/features/commentary/indie-film-distribution-tracks-a-producers-path-1235189265/",
      "pubDate": "Wed, 15 Apr 2026 19:30:00 +0000",
      "source": "IndieWire",
      "sourceId": "indiewire_film",
      "tab": "news"
    },
    {
      "id": "437cce1619",
      "title": "‘Normal’ Review: The Jokes — and the Bullets — Fly Freely in Bob Odenkirk’s Latest Action-Hero Role",
      "link": "https://www.indiewire.com/criticism/movies/normal-review-bob-odenkirk-action-1235150125/",
      "pubDate": "Wed, 15 Apr 2026 19:00:00 +0000",
      "source": "IndieWire",
      "sourceId": "indiewire_film",
      "tab": "news"
    },
    {
      "id": "64483b7804",
      "title": "David Lynch’s ‘The Elephant Man,’ Neil Jordan’s ‘The Crying Game’ Among Criterion Collection’s July Physical Media Releases",
      "link": "https://variety.com/2026/film/awards/criterion-july-2026-physical-media-crying-game-elephant-man-1236722635/",
      "pubDate": "Wed, 15 Apr 2026 18:20:47 +0000",
      "source": "Variety Contenders",
      "sourceId": "variety_cont",
      "tab": "awards"
    },
    {
      "id": "201a27a071",
      "title": "‘Amrum’ Review: Fatih Akin’s World War II Coming-of-Age Film Is Unlike Anything He’s Done Before",
      "link": "https://www.indiewire.com/criticism/movies/amrum-review-fatih-akin-1235189194/",
      "pubDate": "Wed, 15 Apr 2026 18:00:00 +0000",
      "source": "IndieWire",
      "sourceId": "indiewire_film",
      "tab": "news"
    },
    {
      "id": "85f0e48d55",
      "title": "Seattle International Film Festival Announces 2026 Lineup with ‘The Invite,’ ‘I Love Boosters,’ and More",
      "link": "https://www.indiewire.com/news/festivals/seattle-international-film-festival-siff-2026-lineup-1235189221/",
      "pubDate": "Wed, 15 Apr 2026 17:05:00 +0000",
      "source": "IndieWire",
      "sourceId": "indiewire_film",
      "tab": "news"
    },
    {
      "id": "0dc4bbf4d3",
      "title": "How ‘Parks and Recreation’ Went from Nearly Canceled to Enduring Comedy Classic",
      "link": "https://www.indiewire.com/features/commentary/parks-and-recreation-nearly-canceled-comedy-classic-1235189161/",
      "pubDate": "Wed, 15 Apr 2026 17:00:00 +0000",
      "source": "IndieWire TV",
      "sourceId": "indiewire_tv",
      "tab": "news"
    },
    {
      "id": "3955869330",
      "title": "MDR versteigert TV-Requisiten aus seinem Fundus",
      "link": "https://www.dwdl.de/nachrichten/106183/mdr_versteigert_tvrequisiten_aus_seinem_fundus_/",
      "pubDate": "Wed, 15 Apr 2026 17:46:00 +0200",
      "source": "DWDL",
      "sourceId": "dwdl_all",
      "tab": "german"
    },
    {
      "id": "f8647fb246",
      "title": "George Clooney Chaplin Gala Tribute Reveals 2026 Presenters",
      "link": "https://www.indiewire.com/awards/industry/george-clooney-chaplin-gala-presenters-2026-1235188980/",
      "pubDate": "Wed, 15 Apr 2026 14:30:00 +0000",
      "source": "IndieWire Awards",
      "sourceId": "indiewire_awards",
      "tab": "awards"
    },
    {
      "id": "f96cfceda4",
      "title": "Neues Beetz-Label startet mit Wacken-Doku bei MagentaTV",
      "link": "https://www.dwdl.de/nachrichten/106182/neues_beetzlabel_startet_mit_wackendoku_bei_magentatv/",
      "pubDate": "Wed, 15 Apr 2026 15:40:00 +0200",
      "source": "DWDL",
      "sourceId": "dwdl_all",
      "tab": "german"
    },
    {
      "id": "355e3a14a6",
      "title": "RTL holt auch Ulrich Wetzel in die Primetime",
      "link": "https://www.dwdl.de/nachrichten/106181/rtl_holt_auch_ulrich_wetzel_in_die_primetime/",
      "pubDate": "Wed, 15 Apr 2026 15:17:00 +0200",
      "source": "DWDL",
      "sourceId": "dwdl_all",
      "tab": "german"
    },
    {
      "id": "848328110e",
      "title": "Schumacher, Matthäus, Messner: Sky stellt neue Doku-Projekte vor",
      "link": "https://www.dwdl.de/nachrichten/106179/schumacher_matthaeus_messner_sky_stellt_neue_dokuprojekte_vor/",
      "pubDate": "Wed, 15 Apr 2026 14:22:00 +0200",
      "source": "DWDL",
      "sourceId": "dwdl_all",
      "tab": "german"
    },
    {
      "id": "419cafcd8d",
      "title": "The Final Countdown? RTL, Sky und die Entscheidung der EU",
      "link": "https://www.dwdl.de/nachrichten/106177/the_final_countdown_rtl_sky_und_die_entscheidung_der_eu/",
      "pubDate": "Wed, 15 Apr 2026 13:57:00 +0200",
      "source": "DWDL",
      "sourceId": "dwdl_all",
      "tab": "german"
    },
    {
      "id": "b0812363c5",
      "title": "Six Gen Z cinemagoers discuss cinema prices, release windows confusion and celebrity interviews",
      "link": "https://www.screendaily.com/features/six-gen-z-cinemagoers-discuss-cinema-prices-release-windows-confusion-and-celebrity-interviews/5215650.article",
      "pubDate": "Wed, 15 Apr 2026 11:00:00 GMT",
      "source": "Screen Daily",
      "sourceId": "screen_main",
      "tab": "industry"
    },
    {
      "id": "7e1391387d",
      "title": "Silvan-Pierre Leirich verlässt \"AWZ\" nach fast 20 Jahren",
      "link": "https://www.dwdl.de/nachrichten/106178/silvanpierre_leirich_verlaesst_awz_nach_fast_20_jahren/",
      "pubDate": "Wed, 15 Apr 2026 12:56:00 +0200",
      "source": "DWDL",
      "sourceId": "dwdl_all",
      "tab": "german"
    },
    {
      "id": "119655758b",
      "title": "Cannes Docs Showcase Unveils Circle Doc Accelerator Projects (EXCLUSIVE)",
      "link": "https://variety.com/2026/film/festivals/cannes-docs-showcase-circle-doc-accelerator-projects-2026-1236720917/",
      "pubDate": "Wed, 15 Apr 2026 10:00:00 +0000",
      "source": "Variety Festivals",
      "sourceId": "variety_fest",
      "tab": "festivals"
    },
    {
      "id": "dbd43a029a",
      "title": "Gigantisches \"Rex\"-Comeback, Rettung für Mediashop in Sicht",
      "link": "https://www.dwdl.de/austriaupdate/106176/gigantisches_rexcomeback_rettung_fuer_mediashop_in_sicht/",
      "pubDate": "Wed, 15 Apr 2026 11:01:00 +0200",
      "source": "DWDL",
      "sourceId": "dwdl_all",
      "tab": "german"
    },
    {
      "id": "61ac502b31",
      "title": "Gemeinsame Morgenstrecke von RTL und ntv startet Anfang Mai",
      "link": "https://www.dwdl.de/nachrichten/106169/gemeinsame_morgenstrecke_von_rtl_und_ntv_startet_anfang_mai/",
      "pubDate": "Wed, 15 Apr 2026 10:15:00 +0200",
      "source": "DWDL Nachrichten",
      "sourceId": "dwdl_nachrichten",
      "tab": "german"
    },
    {
      "id": "6f0f90ba25",
      "title": "DFB.TV: Deutscher Fußball-Bund startet eigenen Pay-TV-Sender",
      "link": "https://www.dwdl.de/nachrichten/106167/dfbtv_deutscher_fussballbund_startet_eigenen_paytvsender/",
      "pubDate": "Wed, 15 Apr 2026 06:00:00 +0200",
      "source": "DWDL Nachrichten",
      "sourceId": "dwdl_nachrichten",
      "tab": "german"
    },
    {
      "id": "917fb3d5fe",
      "title": "Jason Bateman and Linda Cardellini Launch Supporting Acting Emmys Push for ‘DTF St. Louis’ (EXCLUSIVE)",
      "link": "https://variety.com/2026/tv/awards/jason-bateman-linda-cardellini-emmys-dtf-st-louis-supporting-1236721887/",
      "pubDate": "Wed, 15 Apr 2026 00:31:05 +0000",
      "source": "Variety Contenders",
      "sourceId": "variety_cont",
      "tab": "awards"
    },
    {
      "id": "926a2346b6",
      "title": "‘Train to Busan’ Director Yeon Sang-ho’s Cannes-Bound Virus Thriller ‘Colony’ Unveils First Trailer (EXCLUSIVE)",
      "link": "https://variety.com/2026/film/festivals/yeon-sang-ho-cannes-virus-thriller-colony-trailer-1236721095/",
      "pubDate": "Wed, 15 Apr 2026 00:00:00 +0000",
      "source": "Variety Festivals",
      "sourceId": "variety_fest",
      "tab": "festivals"
    },
    {
      "id": "80ae65faa8",
      "title": "Is It Finally Time for ‘Survivor’ to Win the Emmy? Season 50 Makes Its Strongest Case Yet",
      "link": "https://variety.com/2026/tv/awards/survivor-season-50-emmys-win-chances-jeff-probst-1236720551/",
      "pubDate": "Tue, 14 Apr 2026 22:30:00 +0000",
      "source": "Variety Contenders",
      "sourceId": "variety_cont",
      "tab": "awards"
    },
    {
      "id": "76cb3396b9",
      "title": "What ‘The Pitt’ Gets Right (and Wrong) About ‘Pittsburghese’",
      "link": "https://www.indiewire.com/features/interviews/the-pitt-pittsburghese-accent-katherine-lanasa-1235188754/",
      "pubDate": "Tue, 14 Apr 2026 20:00:00 +0000",
      "source": "IndieWire TV",
      "sourceId": "indiewire_tv",
      "tab": "news"
    },
    {
      "id": "0e79af90c2",
      "title": "Netflix’s ‘Lord of the Flies’ Enters 12 Emmy Categories, Positioning Young Cast for Potential Nominations (EXCLUSIVE)",
      "link": "https://variety.com/2026/tv/awards/lord-of-the-flies-netflix-emmys-submissions-1236720654/",
      "pubDate": "Tue, 14 Apr 2026 19:00:00 +0000",
      "source": "Variety Contenders",
      "sourceId": "variety_cont",
      "tab": "awards"
    },
    {
      "id": "24ba8eb872",
      "title": "Westermann und Alsmann blicken auf \"Zimmer frei!\" zurück",
      "link": "https://www.dwdl.de/nachrichten/106172/westermann_und_alsmann_blicken_auf_zimmer_frei_zurueck/",
      "pubDate": "Tue, 14 Apr 2026 19:11:00 +0200",
      "source": "DWDL Nachrichten",
      "sourceId": "dwdl_nachrichten",
      "tab": "german"
    },
    {
      "id": "0a129d9a6c",
      "title": "‘The Audacity’ Sets Emmy Strategy With Drama Series Push and Lead Campaigns for Billy Magnussen and Sarah Goldberg (EXCLUSIVE)",
      "link": "https://variety.com/2026/tv/awards/the-audacity-emmys-billy-magnussen-sarah-goldberg-lead-1236720791/",
      "pubDate": "Tue, 14 Apr 2026 16:15:00 +0000",
      "source": "Variety Contenders",
      "sourceId": "variety_cont",
      "tab": "awards"
    },
    {
      "id": "c9051d60ca",
      "title": "Santa Barbara International Film Festival Announces 2027 Dates (Exclusive)",
      "link": "https://www.hollywoodreporter.com/movies/movie-news/santa-barbara-film-festival-2027-dates-exclusive-1236563763/",
      "pubDate": "Tue, 14 Apr 2026 16:00:00 +0000",
      "source": "THR Awards",
      "sourceId": "thr_awards",
      "tab": "awards"
    },
    {
      "id": "704c6f749a",
      "title": "Neuer Medienrat konstituiert sich, Wappler ist Vorsitzende",
      "link": "https://www.dwdl.de/nachrichten/106171/neuer_medienrat_konstituiert_sich_wappler_ist_vorsitzende/",
      "pubDate": "Tue, 14 Apr 2026 17:21:00 +0200",
      "source": "DWDL Nachrichten",
      "sourceId": "dwdl_nachrichten",
      "tab": "german"
    },
    {
      "id": "d8888aeae4",
      "title": "Kurosawa Kiyoshi’s ‘The Samurai and the Prisoner’ Lands U.S. Deal With Janus Films Ahead of Cannes Premiere",
      "link": "https://variety.com/2026/film/festivals/kurosawa-kiyoshi-samurai-prisoner-janus-films-cannes-1236720906/",
      "pubDate": "Tue, 14 Apr 2026 15:00:00 +0000",
      "source": "Variety Festivals",
      "sourceId": "variety_fest",
      "tab": "festivals"
    },
    {
      "id": "500707fd8a",
      "title": "\"The Hunt\": Bei ProSieben spielen Promis bald Fangen",
      "link": "https://www.dwdl.de/nachrichten/106170/the_hunt_bei_prosieben_spielen_promis_bald_fangen/",
      "pubDate": "Tue, 14 Apr 2026 16:36:00 +0200",
      "source": "DWDL Nachrichten",
      "sourceId": "dwdl_nachrichten",
      "tab": "german"
    },
    {
      "id": "b82b17f225",
      "title": "\"DSDS\" findet sein Publikum vor allem im linearen TV",
      "link": "https://www.dwdl.de/zahlenzentrale/106160/dsds_findet_sein_publikum_vor_allem_im_linearen_tv/",
      "pubDate": "Tue, 14 Apr 2026 15:30:00 +0200",
      "source": "DWDL Nachrichten",
      "sourceId": "dwdl_nachrichten",
      "tab": "german"
    },
    {
      "id": "cd7cb06018",
      "title": "Bauers Rückzug: Mit Websites sei kein Geld mehr zu verdienen",
      "link": "https://www.dwdl.de/nachrichten/106168/bauers_rueckzug_mit_websites_sei_kein_geld_mehr_zu_verdienen/",
      "pubDate": "Tue, 14 Apr 2026 15:11:00 +0200",
      "source": "DWDL Nachrichten",
      "sourceId": "dwdl_nachrichten",
      "tab": "german"
    },
    {
      "id": "dc01961306",
      "title": "Taylor Swift Leads 2026 American Music Awards With Eight Nominations",
      "link": "https://www.hollywoodreporter.com/music/music-news/american-music-awards-2026-nominations-list-1236563285/",
      "pubDate": "Tue, 14 Apr 2026 12:00:00 +0000",
      "source": "THR Awards",
      "sourceId": "thr_awards",
      "tab": "awards"
    },
    {
      "id": "6ca1fb4054",
      "title": "Spanish Cinema Booming Thanks to Robust Incentives, Spectacular Natural Locations, Thriving Creative Ecosystem",
      "link": "https://variety.com/2026/film/festivals/spain-sirat-decorado-goya-goes-to-new-spanish-films-1236719645/",
      "pubDate": "Tue, 14 Apr 2026 10:54:50 +0000",
      "source": "Variety Festivals",
      "sourceId": "variety_fest",
      "tab": "festivals"
    },
    {
      "id": "87004d35ab",
      "title": "Alex Garland’s ‘Elden Ring’ filming in UK for A24, DNA Films",
      "link": "https://www.screendaily.com/news/alex-garlands-elden-ring-filming-in-uk-for-a24-dna-films/5215469.article",
      "pubDate": "Tue, 14 Apr 2026 10:30:00 GMT",
      "source": "Screen Daily",
      "sourceId": "screen_main",
      "tab": "industry"
    },
    {
      "id": "16ad10fb46",
      "title": "Was aktuell auf Instagram und TikTok viral geht",
      "link": "https://www.dwdl.de/magazin/105105/was_aktuell_auf_instagram_und_tiktok_viral_geht/",
      "pubDate": "Tue, 14 Apr 2026 11:39:00 +0200",
      "source": "DWDL Magazin",
      "sourceId": "dwdl_magazin",
      "tab": "german"
    },
    {
      "id": "288e3f70ea",
      "title": "Tokyo International Film Festival Names Hisamatsu Takeo as New Director",
      "link": "https://variety.com/2026/film/festivals/tokyo-international-film-festival-hisamatsu-takeo-director-1236720290/",
      "pubDate": "Tue, 14 Apr 2026 09:00:00 +0000",
      "source": "Variety Festivals",
      "sourceId": "variety_fest",
      "tab": "festivals"
    },
    {
      "id": "3443cdf731",
      "title": "Bei der geplanten BR-Reform braut sich ein Streit zusammen",
      "link": "https://www.dwdl.de/magazin/106104/bei_der_geplanten_brreform_braut_sich_ein_streit_zusammen/",
      "pubDate": "Tue, 14 Apr 2026 10:49:00 +0200",
      "source": "DWDL Magazin",
      "sourceId": "dwdl_magazin",
      "tab": "german"
    },
    {
      "id": "1670fe772f",
      "title": "Far East Film Festival’s Focus Asia Reveals 19 Projects, Debuts $20,000 White Light Award",
      "link": "https://variety.com/2026/film/festivals/far-east-film-festival-focus-asia-2026-projects-1236720898/",
      "pubDate": "Tue, 14 Apr 2026 01:58:48 +0000",
      "source": "Variety Festivals",
      "sourceId": "variety_fest",
      "tab": "festivals"
    },
    {
      "id": "4b8a87e316",
      "title": "Every Episode of ‘Euphoria,’ Ranked",
      "link": "https://www.indiewire.com/lists/euphoria-every-episode-ranking/",
      "pubDate": "Mon, 13 Apr 2026 18:00:00 +0000",
      "source": "IndieWire TV",
      "sourceId": "indiewire_tv",
      "tab": "news"
    },
    {
      "id": "36cd5a73ca",
      "title": "‘Linka Linka’ Wins Firebird Award and Fipresci Prize at 50th Hong Kong Film Festival",
      "link": "https://variety.com/2026/film/festivals/hong-kong-film-festival-winners-linka-linka-1236720255/",
      "pubDate": "Mon, 13 Apr 2026 13:26:05 +0000",
      "source": "Variety Festivals",
      "sourceId": "variety_fest",
      "tab": "festivals"
    },
    {
      "id": "b97ef96f67",
      "title": "‘Euphoria,’ and How Angus Cloud’s Death Impacted Season 3",
      "link": "https://www.indiewire.com/features/interviews/euphoria-angus-cloud-fentanyl-impacted-season-3-1235188504/",
      "pubDate": "Mon, 13 Apr 2026 13:00:00 +0000",
      "source": "IndieWire TV",
      "sourceId": "indiewire_tv",
      "tab": "news"
    },
    {
      "id": "f429b66f20",
      "title": "Russo Brothers’ AGBO Sets ‘Major’ SXSW London Partnership Ahead of ‘Avengers: Doomsday’ Release",
      "link": "https://variety.com/2026/film/festivals/agbo-sxsw-london-russo-brothers-1236720137/",
      "pubDate": "Mon, 13 Apr 2026 08:59:14 +0000",
      "source": "Variety Festivals",
      "sourceId": "variety_fest",
      "tab": "festivals"
    },
    {
      "id": "c5d2ae7923",
      "title": "‘DTF St. Louis’ Review: A Sensational Finale Reveals Far More Than Who Dun It — Spoilers",
      "link": "https://www.indiewire.com/criticism/shows/dtf-st-louis-episode-7-review-finale-explained-spoilers-1235188434/",
      "pubDate": "Mon, 13 Apr 2026 01:00:00 +0000",
      "source": "IndieWire TV",
      "sourceId": "indiewire_tv",
      "tab": "news"
    },
    {
      "id": "e9e5cc55cc",
      "title": "Zendaya and Jean Smart Eye First-Ever Emmy Sweep by Women for a Single Series. Will They Pull It Off?",
      "link": "https://variety.com/2026/tv/awards/zendaya-jean-smart-emmys-sweep-euphoria-hacks-1236719640/",
      "pubDate": "Sun, 12 Apr 2026 22:00:00 +0000",
      "source": "Variety Contenders",
      "sourceId": "variety_cont",
      "tab": "awards"
    },
    {
      "id": "84b34bfdf3",
      "title": "The Three Instruments That Lay the Curse in the ‘Something Very Bad Is Going to Happen’ Score",
      "link": "https://www.indiewire.com/features/craft/something-very-bad-is-going-to-happen-music-score-interview-1235187991/",
      "pubDate": "Sat, 11 Apr 2026 15:00:00 +0000",
      "source": "IndieWire TV",
      "sourceId": "indiewire_tv",
      "tab": "news"
    },
    {
      "id": "951e8fa10b",
      "title": "Paradise Lost: Abschied vom Fernseh-Fernweh?",
      "link": "https://www.dwdl.de/hauptstadtstudio/106117/paradise_lost_abschied_vom_fernsehfernweh/",
      "pubDate": "Sat, 11 Apr 2026 08:05:00 +0200",
      "source": "DWDL Magazin",
      "sourceId": "dwdl_magazin",
      "tab": "german"
    },
    {
      "id": "917d98b31a",
      "title": "Inside the New Film Stock Kodak Created for ‘Euphoria’ Season 3",
      "link": "https://www.indiewire.com/news/breaking-news/euphoria-season-3-kodak-new-film-stock-1235188424/",
      "pubDate": "Fri, 10 Apr 2026 20:30:00 +0000",
      "source": "IndieWire TV",
      "sourceId": "indiewire_tv",
      "tab": "news"
    },
    {
      "id": "3ac3c62348",
      "title": "‘The Audacity’ Review: AMC’s Clever, Pitch-Black Comedy Gets Trapped in a Tech Bubble",
      "link": "https://www.indiewire.com/criticism/shows/the-audacity-review-amc-comedy-series-1235187504/",
      "pubDate": "Fri, 10 Apr 2026 18:00:00 +0000",
      "source": "IndieWire TV",
      "sourceId": "indiewire_tv",
      "tab": "news"
    },
    {
      "id": "dfc12da246",
      "title": "Branchen-Trend: Sind Mikro-Dramen ein Mega-Business?",
      "link": "https://www.dwdl.de/industry/106121/branchentrend_sind_mikrodramen_ein_megabusiness/",
      "pubDate": "Fri, 10 Apr 2026 08:00:00 +0200",
      "source": "DWDL Magazin",
      "sourceId": "dwdl_magazin",
      "tab": "german"
    },
    {
      "id": "891f7be354",
      "title": "Tony Awards Eligibility: Ebon Moss-Bachrach Secures Featured Actor Placement for ‘Dog Day Afternoon’",
      "link": "https://variety.com/2026/legit/awards/ebon-moss-bachrach-tony-awards-dog-day-afternoon-1236713007/",
      "pubDate": "Thu, 09 Apr 2026 23:24:22 +0000",
      "source": "Variety Contenders",
      "sourceId": "variety_cont",
      "tab": "awards"
    },
    {
      "id": "5685fc4248",
      "title": "‘Live With Kelly and Mark’ Post-Oscars Episode Viewership Grows 13% Over Last Year (EXCLUSIVE)",
      "link": "https://variety.com/2026/tv/news/live-with-kelly-and-mark-post-oscars-episode-ratings-1236712982/",
      "pubDate": "Thu, 09 Apr 2026 22:34:00 +0000",
      "source": "Variety Contenders",
      "sourceId": "variety_cont",
      "tab": "awards"
    },
    {
      "id": "5124df99b5",
      "title": "Erika Alexander Eyes Supporting Comedy Emmy for ‘The Fall and Rise of Reggie Dinkins’ (EXCLUSIVE)",
      "link": "https://variety.com/2026/tv/awards/erika-alexander-supporting-comedy-emmys-reggie-dinkins-1236704731/",
      "pubDate": "Thu, 09 Apr 2026 20:06:43 +0000",
      "source": "Variety Contenders",
      "sourceId": "variety_cont",
      "tab": "awards"
    },
    {
      "id": "aa8a3c4c2c",
      "title": "Emmy Predictions: ‘The Pitt,’ ‘Pluribus’ and ‘Beef’ Gain Momentum as ‘Shrinking’ Looks to Challenge ‘Hacks’",
      "link": "https://variety.com/lists/2026-emmys-predictions/",
      "pubDate": "Thu, 09 Apr 2026 19:10:00 +0000",
      "source": "Variety Contenders",
      "sourceId": "variety_cont",
      "tab": "awards"
    },
    {
      "id": "3f2b191003",
      "title": "‘Heated Rivalry,’ ‘Jimmy Kimmel Live!,’ ‘The Pitt’ Among Nominees for 2026 Peabody Awards",
      "link": "https://www.hollywoodreporter.com/tv/tv-news/2026-peabody-awards-nominations-entertainment-1236560130/",
      "pubDate": "Thu, 09 Apr 2026 17:01:37 +0000",
      "source": "THR Awards",
      "sourceId": "thr_awards",
      "tab": "awards"
    },
    {
      "id": "1302e4b755",
      "title": "Pink to Host Tony Awards",
      "link": "https://www.hollywoodreporter.com/tv/tv-news/pink-tony-awards-1236560101/",
      "pubDate": "Thu, 09 Apr 2026 16:59:23 +0000",
      "source": "THR Awards",
      "sourceId": "thr_awards",
      "tab": "awards"
    },
    {
      "id": "629327c969",
      "title": "Cannes Chief Thierry Frémaux Confirms He’s Still Chasing James Gray’s ‘Paper Tiger,’ Starring Scarlett Johansson and Adam Driver, for This Year’s Fest: It’s a ‘Wonderful Film’ and ‘Very Indie’",
      "link": "https://variety.com/2026/film/festivals/cannes-thierry-fremaux-wants-james-gray-paper-tiger-lineup-1236712322/",
      "pubDate": "Thu, 09 Apr 2026 14:18:42 +0000",
      "source": "Variety Festivals",
      "sourceId": "variety_fest",
      "tab": "festivals"
    },
    {
      "id": "10e3454f72",
      "title": "Cannes Film Festival 2026 Lineup: Asghar Farhadi, Pedro Almodóvar, Ira Sachs, Hirokazu Kore-eda Set for Auteur-Driven Competition",
      "link": "https://variety.com/2026/film/festivals/cannes-film-festival-2026-lineup-1236711319/",
      "pubDate": "Thu, 09 Apr 2026 08:50:00 +0000",
      "source": "Variety Festivals",
      "sourceId": "variety_fest",
      "tab": "festivals"
    },
    {
      "id": "7228f449e8",
      "title": "\"Rex\"-Produzent Oliver Auspitz: \"Habe offene Türen eingerannt\"",
      "link": "https://www.dwdl.de/interviews/106100/rexproduzent_oliver_auspitz_habe_offene_tueren_eingerannt/",
      "pubDate": "Thu, 09 Apr 2026 00:01:00 +0200",
      "source": "DWDL Interviews",
      "sourceId": "dwdl_interviews",
      "tab": "german"
    },
    {
      "id": "d3350ee676",
      "title": "Producers Guild Sets PGA Awards Dates for 2027 and 2028",
      "link": "https://www.hollywoodreporter.com/movies/movie-news/producers-guild-sets-pga-awards-dates-2027-2028-1236558188/",
      "pubDate": "Tue, 07 Apr 2026 23:15:00 +0000",
      "source": "THR Awards",
      "sourceId": "thr_awards",
      "tab": "awards"
    },
    {
      "id": "98b0aee7c2",
      "title": "Oscars Dates Set for 2027 and 2028",
      "link": "https://www.hollywoodreporter.com/movies/movie-news/oscars-dates-2027-2028-1236557925/",
      "pubDate": "Tue, 07 Apr 2026 21:00:00 +0000",
      "source": "THR Awards",
      "sourceId": "thr_awards",
      "tab": "awards"
    },
    {
      "id": "924b796bf7",
      "title": "The Oscars Are Sticking with March — and That Won’t Change for Years",
      "link": "https://www.indiewire.com/awards/industry/oscars-2027-2028-dates-abc-1235187801/",
      "pubDate": "Tue, 07 Apr 2026 21:00:00 +0000",
      "source": "IndieWire Awards",
      "sourceId": "indiewire_awards",
      "tab": "awards"
    },
    {
      "id": "af3b93b9f9",
      "title": "The Emmys Tried to Get a Handle on AI. The Writers Had Notes.",
      "link": "https://www.hollywoodreporter.com/tv/tv-features/emmys-ai-shows-nominees-rooster-comeback-1236557945/",
      "pubDate": "Tue, 07 Apr 2026 20:12:52 +0000",
      "source": "THR Awards",
      "sourceId": "thr_awards",
      "tab": "awards"
    },
    {
      "id": "5c8994663c",
      "title": "Peabody Awards: ‘Mr. Nobody Against Putin,’ ‘Pee-Wee As Himself,’ ‘The Perfect Neighbor’ Among First Set of Nominees",
      "link": "https://www.hollywoodreporter.com/movies/movie-news/2026-peabody-awards-nominees-documentary-news-1236556739/",
      "pubDate": "Tue, 07 Apr 2026 17:00:00 +0000",
      "source": "THR Awards",
      "sourceId": "thr_awards",
      "tab": "awards"
    },
    {
      "id": "0ac4eebbd9",
      "title": "2026 Peabody Award Nominees Include ‘No Other Land,’ ‘The Perfect Neighbor,’ and More",
      "link": "https://www.indiewire.com/awards/results/peabody-award-nominations-2026-1235187687/",
      "pubDate": "Tue, 07 Apr 2026 17:00:00 +0000",
      "source": "IndieWire Awards",
      "sourceId": "indiewire_awards",
      "tab": "awards"
    },
    {
      "id": "8e1e40dd02",
      "title": "2026 News and Documentary Emmys: National Geographic Leads Nominees as ABC, CNN, NBC, ‘2000 Meters to Andriivka’ Land Top Nods",
      "link": "https://www.hollywoodreporter.com/tv/tv-news/2026-news-documentary-emmy-awards-nominations-1236557005/",
      "pubDate": "Tue, 07 Apr 2026 12:30:00 +0000",
      "source": "THR Awards",
      "sourceId": "thr_awards",
      "tab": "awards"
    },
    {
      "id": "dd5c0fefbb",
      "title": "Katja Hofem: \"Der Mut von heute ist der Mainstream von morgen\"",
      "link": "https://www.dwdl.de/visionaeronair/106077/katja_hofem_der_mut_von_heute_ist_der_mainstream_von_morgen/",
      "pubDate": "Tue, 07 Apr 2026 08:37:00 +0200",
      "source": "DWDL Magazin",
      "sourceId": "dwdl_magazin",
      "tab": "german"
    },
    {
      "id": "b881948db6",
      "title": "Emmy Predictions via Feinberg Forecast: Scott’s First Read of the Race",
      "link": "https://www.hollywoodreporter.com/lists/emmys-2026-predictions-feinberg-forecast/",
      "pubDate": "Mon, 06 Apr 2026 23:26:48 +0000",
      "source": "THR Awards",
      "sourceId": "thr_awards",
      "tab": "awards"
    },
    {
      "id": "d1aed87239",
      "title": "Fernsehen zum Mitspielen: Vom Tele-Schuss zum Tele-Troll",
      "link": "https://www.dwdl.de/telegeschichten/106066/fernsehen_zum_mitspielen_vom_teleschuss_zum_teletroll/",
      "pubDate": "Mon, 06 Apr 2026 08:25:00 +0200",
      "source": "DWDL Magazin",
      "sourceId": "dwdl_magazin",
      "tab": "german"
    },
    {
      "id": "5ea16ec708",
      "title": "Fernsehen zum Mitbestimmen: Vom Applaus zur App",
      "link": "https://www.dwdl.de/telegeschichten/106056/fernsehen_zum_mitbestimmen_vom_applaus_zur_app/",
      "pubDate": "Sun, 05 Apr 2026 08:03:00 +0200",
      "source": "DWDL Magazin",
      "sourceId": "dwdl_magazin",
      "tab": "german"
    },
    {
      "id": "a01792ce94",
      "title": "News-Charts: Die kritischen Klicks mit dem Krieg",
      "link": "https://www.dwdl.de/zahlenzentrale/106037/newscharts_die_kritischen_klicks_mit_dem_krieg/",
      "pubDate": "Thu, 02 Apr 2026 08:00:00 +0200",
      "source": "DWDL Magazin",
      "sourceId": "dwdl_magazin",
      "tab": "german"
    },
    {
      "id": "4cd54bdc51",
      "title": "TikTok-News-Charts bei DWDL.de: Die Publisher-Übersicht",
      "link": "https://www.dwdl.de/zahlenzentrale/103612/tiktoknewscharts_bei_dwdlde_die_publisheruebersicht/",
      "pubDate": "Wed, 01 Apr 2026 10:30:00 +0200",
      "source": "DWDL Magazin",
      "sourceId": "dwdl_magazin",
      "tab": "german"
    },
    {
      "id": "a8e557ab92",
      "title": "Besetzung der neuen RBB-Führungsteams erfolgt später",
      "link": "https://www.dwdl.de/magazin/106030/besetzung_der_neuen_rbbfuehrungsteams_erfolgt_spaeter/",
      "pubDate": "Tue, 31 Mar 2026 16:30:00 +0200",
      "source": "DWDL Magazin",
      "sourceId": "dwdl_magazin",
      "tab": "german"
    },
    {
      "id": "c49dcf0362",
      "title": "\"Radikal weiterentwickeln\": Schmitter über Streaming, Sky und Stellenabbau",
      "link": "https://www.dwdl.de/interviews/105997/radikal_weiterentwickeln_schmitter_ueber_streaming_sky_und_stellenabbau/",
      "pubDate": "Mon, 30 Mar 2026 00:02:00 +0200",
      "source": "DWDL Interviews",
      "sourceId": "dwdl_interviews",
      "tab": "german"
    },
    {
      "id": "6651aeb784",
      "title": "Steven Soderbergh’s ‘The Christophers’ Wins Narrative Audience Award at Sonoma International Film Festival 2026",
      "link": "https://www.indiewire.com/awards/industry/the-christophers-audience-award-sonoma-film-festival-2026-1235186476/",
      "pubDate": "Sun, 29 Mar 2026 19:30:00 +0000",
      "source": "IndieWire Awards",
      "sourceId": "indiewire_awards",
      "tab": "awards"
    },
    {
      "id": "0b167d42cc",
      "title": "\"Fun Facts\" mit Marc-Uwe Kling: Dann lachen wir das eben selbst",
      "link": "https://www.dwdl.de/hauptstadtstudio/106000/fun_facts_mit_marcuwe_kling_dann_lachen_wir_das_eben_selbst/",
      "pubDate": "Sat, 28 Mar 2026 08:20:00 +0100",
      "source": "DWDL Magazin",
      "sourceId": "dwdl_magazin",
      "tab": "german"
    },
    {
      "id": "7cd0b1b0af",
      "title": "Das Privileg des Neuen: Die Aufsteiger-Rolle fällt HBO Max zu",
      "link": "https://www.dwdl.de/magazin/105988/das_privileg_des_neuen_die_aufsteigerrolle_faellt_hbo_max_zu/",
      "pubDate": "Fri, 27 Mar 2026 11:09:00 +0100",
      "source": "DWDL Magazin",
      "sourceId": "dwdl_magazin",
      "tab": "german"
    },
    {
      "id": "d8b3bb0017",
      "title": "Beispiel Frankreich: Wie wirkt sich eine Investitionsverpflichtung aus?",
      "link": "https://www.dwdl.de/industry/105990/beispiel_frankreich_wie_wirkt_sich_eine_investitionsverpflichtung_aus/",
      "pubDate": "Fri, 27 Mar 2026 08:32:00 +0100",
      "source": "DWDL Magazin",
      "sourceId": "dwdl_magazin",
      "tab": "german"
    },
    {
      "id": "f76270c0ca",
      "title": "The Good, the Bad, and the Basic Rule Changes Affecting the 2026 Emmys",
      "link": "https://www.indiewire.com/awards/industry/2026-emmys-rule-changes-good-bad-basic-1235186297/",
      "pubDate": "Thu, 26 Mar 2026 21:00:00 +0000",
      "source": "IndieWire Awards",
      "sourceId": "indiewire_awards",
      "tab": "awards"
    },
    {
      "id": "f514ba553d",
      "title": "\"Ohne Haltung wären wir keine Journalisten, sondern Maschinen\"",
      "link": "https://www.dwdl.de/interviews/105952/ohne_haltung_waeren_wir_keine_journalisten_sondern_maschinen/",
      "pubDate": "Thu, 26 Mar 2026 13:00:00 +0100",
      "source": "DWDL Interviews",
      "sourceId": "dwdl_interviews",
      "tab": "german"
    },
    {
      "id": "d3cc02062e",
      "title": "The Television Academy Welcomes Prop Masters Into the Fold",
      "link": "https://www.indiewire.com/awards/industry/television-academy-prop-masters-join-vote-emmys-1235185815/",
      "pubDate": "Tue, 24 Mar 2026 13:00:00 +0000",
      "source": "IndieWire Awards",
      "sourceId": "indiewire_awards",
      "tab": "awards"
    },
    {
      "id": "b1f2731279",
      "title": "\"Wir wollen Streaming und Fernsehen in Zukunft getrennter betrachten\"",
      "link": "https://www.dwdl.de/interviews/105929/wir_wollen_streaming_und_fernsehen_in_zukunft_getrennter_betrachten/",
      "pubDate": "Tue, 24 Mar 2026 08:00:00 +0100",
      "source": "DWDL Interviews",
      "sourceId": "dwdl_interviews",
      "tab": "german"
    },
    {
      "id": "b085991cc8",
      "title": "SXSW 2026 Awards: ‘Over Your Dead Body’ and ‘Plantman & Blondie’ Take Audience Awards",
      "link": "https://www.indiewire.com/awards/results/sxsw-2026-film-tv-awards-winners-list-1235185256/",
      "pubDate": "Thu, 19 Mar 2026 09:30:00 +0000",
      "source": "IndieWire Awards",
      "sourceId": "indiewire_awards",
      "tab": "awards"
    },
    {
      "id": "7e6b6f24d3",
      "title": "Let’s End the 2026 Oscars Cycle with Some Optimism",
      "link": "https://www.indiewire.com/awards/industry/black-best-director-oscar-winner-ryan-coogler-1235185111/",
      "pubDate": "Wed, 18 Mar 2026 22:00:00 +0000",
      "source": "IndieWire Awards",
      "sourceId": "indiewire_awards",
      "tab": "awards"
    },
    {
      "id": "057794fc0c",
      "title": "\"Wer sagt, der Dschungel sei krass, hat 'Survivor' noch nicht gesehen\"",
      "link": "https://www.dwdl.de/interviews/105845/wer_sagt_der_dschungel_sei_krass_hat_survivor_noch_nicht_gesehen/",
      "pubDate": "Wed, 18 Mar 2026 12:09:00 +0100",
      "source": "DWDL Interviews",
      "sourceId": "dwdl_interviews",
      "tab": "german"
    },
    {
      "id": "d0e5184b83",
      "title": "Why ‘Sinners’ Never Caught Up with ‘One Battle After Another’",
      "link": "https://www.indiewire.com/awards/industry/why-sinners-could-not-beat-one-battle-after-another-oscars-1235184798/",
      "pubDate": "Mon, 16 Mar 2026 22:10:00 +0000",
      "source": "IndieWire Awards",
      "sourceId": "indiewire_awards",
      "tab": "awards"
    },
    {
      "id": "68b8aea115",
      "title": "If This Oscars Was About as Good as It Gets, Why Did Things Feel Off Inside the Ceremony?",
      "link": "https://www.indiewire.com/awards/industry/2026-oscars-behind-the-scenes-inside-dolby-theatre-1235184809/",
      "pubDate": "Mon, 16 Mar 2026 19:20:00 +0000",
      "source": "IndieWire Awards",
      "sourceId": "indiewire_awards",
      "tab": "awards"
    },
    {
      "id": "7c594b4270",
      "title": "\"Gutes Programm zu produzieren ist allein kein gutes Geschäft mehr\"",
      "link": "https://www.dwdl.de/interviews/105718/gutes_programm_zu_produzieren_ist_allein_kein_gutes_geschaeft_mehr/",
      "pubDate": "Thu, 05 Mar 2026 08:20:00 +0100",
      "source": "DWDL Interviews",
      "sourceId": "dwdl_interviews",
      "tab": "german"
    },
    {
      "id": "0d227bd0ef",
      "title": "\"Unser Konklave war intensiv\": Wie ARD & ZDF ihre Sender neu sortieren",
      "link": "https://www.dwdl.de/interviews/105734/unser_konklave_war_intensiv_wie_ard__zdf_ihre_sender_neu_sortieren/",
      "pubDate": "Wed, 04 Mar 2026 13:00:00 +0100",
      "source": "DWDL Interviews",
      "sourceId": "dwdl_interviews",
      "tab": "german"
    },
    {
      "id": "df1469850d",
      "title": "\"Wir wollen perspektivisch auch für den externen Markt produzieren\"",
      "link": "https://www.dwdl.de/interviews/105683/wir_wollen_perspektivisch_auch_fuer_den_externen_markt_produzieren/",
      "pubDate": "Tue, 03 Mar 2026 07:45:00 +0100",
      "source": "DWDL Interviews",
      "sourceId": "dwdl_interviews",
      "tab": "german"
    },
    {
      "id": "d455ee58a1",
      "title": "\"Irgendwann wird der Spagat so groß, dass es im Schritt reißt\"",
      "link": "https://www.dwdl.de/interviews/105682/irgendwann_wird_der_spagat_so_gross_dass_es_im_schritt_reisst/",
      "pubDate": "Mon, 02 Mar 2026 08:01:00 +0100",
      "source": "DWDL Interviews",
      "sourceId": "dwdl_interviews",
      "tab": "german"
    },
    {
      "id": "997c18a8ba",
      "title": "Dimitrij Schaad: \"Reine Realität ist darstellerisch irre boring\"",
      "link": "https://www.dwdl.de/interviews/105652/dimitrij_schaad_reine_realitaet_ist_darstellerisch_irre_boring/",
      "pubDate": "Wed, 25 Feb 2026 15:34:00 +0100",
      "source": "DWDL Interviews",
      "sourceId": "dwdl_interviews",
      "tab": "german"
    },
    {
      "id": "e2468f088a",
      "title": "Eren M. Güvercin: \"Die Frage zu meiner Identität macht mich müde\"",
      "link": "https://www.dwdl.de/interviews/105590/eren_m_guevercin_die_frage_zu_meiner_identitaet_macht_mich_muede/",
      "pubDate": "Fri, 20 Feb 2026 08:16:00 +0100",
      "source": "DWDL Interviews",
      "sourceId": "dwdl_interviews",
      "tab": "german"
    },
    {
      "id": "2e0141e228",
      "title": "\"Wir haben den Flurfunk digitalisiert\"",
      "link": "https://www.dwdl.de/interviews/105545/wir_haben_den_flurfunk_digitalisiert/",
      "pubDate": "Thu, 19 Feb 2026 00:02:00 +0100",
      "source": "DWDL Interviews",
      "sourceId": "dwdl_interviews",
      "tab": "german"
    },
    {
      "id": "6e50a9619d",
      "title": "\"Lieber Platzhirsch in konkreten Genres als beliebig zu werden\"",
      "link": "https://www.dwdl.de/interviews/105525/lieber_platzhirsch_in_konkreten_genres_als_beliebig_zu_werden/",
      "pubDate": "Wed, 18 Feb 2026 10:07:00 +0100",
      "source": "DWDL Interviews",
      "sourceId": "dwdl_interviews",
      "tab": "german"
    },
    {
      "id": "7205e7338b",
      "title": "Krise? \"Wir sind mitten im Golden Age of Streaming\"",
      "link": "https://www.dwdl.de/interviews/105405/krise_wir_sind_mitten_im_golden_age_of_streaming/",
      "pubDate": "Tue, 10 Feb 2026 00:00:00 +0100",
      "source": "DWDL Interviews",
      "sourceId": "dwdl_interviews",
      "tab": "german"
    },
    {
      "id": "f9e3eb856d",
      "title": "\"Einige warten vielleicht sogar schon darauf, dass wir scheitern\"",
      "link": "https://www.dwdl.de/interviews/105444/einige_warten_vielleicht_sogar_schon_darauf_dass_wir_scheitern/",
      "pubDate": "Mon, 09 Feb 2026 07:41:00 +0100",
      "source": "DWDL Interviews",
      "sourceId": "dwdl_interviews",
      "tab": "german"
    },
    {
      "id": "e6b1740757",
      "title": "Texas-Based Indie Drama ‘Due West’ Picks Up Best Feature Wins At Burbank & El Paso Festivals As Film Seeks Distributor",
      "link": "https://deadline.com/2025/10/due-west-burbank-el-paso-festival-wins-distribution-1236574709/",
      "pubDate": "Thu, 09 Oct 2025 17:07:30 +0000",
      "source": "Deadline Festivals",
      "sourceId": "deadline_fest",
      "tab": "festivals"
    },
    {
      "id": "fff60a7610",
      "title": "Nightmares Film Festival Unveils Horror-Filled 10th Anniversary Programming Slate",
      "link": "https://deadline.com/2025/10/nightmares-film-festival-10th-anniversary-programming-2025-1236568160/",
      "pubDate": "Thu, 02 Oct 2025 01:33:50 +0000",
      "source": "Deadline Festivals",
      "sourceId": "deadline_fest",
      "tab": "festivals"
    },
    {
      "id": "76560f27a3",
      "title": "LALIFF Sets 2025 Film Festival Lineup With Gael García Bernal & Diego Luna-Produced Doc ‘ASCO: Without Permission’ To Open",
      "link": "https://deadline.com/2025/04/laliff-film-festival-2025-lineup-1236381258/",
      "pubDate": "Wed, 30 Apr 2025 17:00:00 +0000",
      "source": "Deadline Festivals",
      "sourceId": "deadline_fest",
      "tab": "festivals"
    },
    {
      "id": "34a03ad998",
      "title": "40th Santa Barbara International Film Festival Winners — Full List",
      "link": "https://deadline.com/2025/02/40th-santa-barbara-international-film-festival-winners-list-1236291027/",
      "pubDate": "Sat, 15 Feb 2025 20:25:18 +0000",
      "source": "Deadline Festivals",
      "sourceId": "deadline_fest",
      "tab": "festivals"
    },
    {
      "id": "e6af07170d",
      "title": "Filmocracy Lives on as Part of Entertainment Oxygen’s eoFlix Platform",
      "link": "https://www.indiewire.com/news/breaking-news/filmocracy-now-part-of-eoflix-1235062618/",
      "pubDate": "Mon, 04 Nov 2024 21:30:00 +0000",
      "source": "IndieWire Festivals",
      "sourceId": "indiewire_fest",
      "tab": "festivals"
    },
    {
      "id": "9ae00185e2",
      "title": "Venice Film Festival Names Juries For Orizzonti and ‘Luigi De Laurentiis’ Awards",
      "link": "https://deadline.com/2024/07/venice-international-film-festival-juries-for-orizzonti-luigi-de-laurentiis-awards-1236016591/",
      "pubDate": "Sat, 20 Jul 2024 13:54:23 +0000",
      "source": "Deadline Festivals",
      "sourceId": "deadline_fest",
      "tab": "festivals"
    },
    {
      "id": "6e45a48751",
      "title": "From Mega-Mergers To (More) Union Strife, India To Israel: Ten Storylines Set To Dominate The International Media Biz In 2024",
      "link": "https://deadline.com/2024/01/paramount-warner-bros-discovery-india-israel-news-stories-2024-1235669180/",
      "pubDate": "Mon, 01 Jan 2024 10:21:43 +0000",
      "source": "Deadline Festivals",
      "sourceId": "deadline_fest",
      "tab": "festivals"
    },
    {
      "id": "f59e2cbb18",
      "title": "Jackson Hole Film Festival Launches Via Partnership With Hamptons Fest Organizers",
      "link": "https://deadline.com/2023/11/jackson-hole-wyoming-film-festival-hamptons-partnership-1235612163/",
      "pubDate": "Wed, 15 Nov 2023 15:00:00 +0000",
      "source": "Deadline Festivals",
      "sourceId": "deadline_fest",
      "tab": "festivals"
    },
    {
      "id": "8cbd23ec76",
      "title": "‘The Boys’ Director Chung Ji-Young: “For People Who Have Authority In Korea, I Am Their Public Enemy No. 1” – London East Asia Film Festival",
      "link": "https://deadline.com/2023/10/the-boys-director-chung-ji-young-korea-public-enemy-no-1-london-east-asian-film-festival-1235577600/",
      "pubDate": "Thu, 19 Oct 2023 16:26:26 +0000",
      "source": "Deadline Festivals",
      "sourceId": "deadline_fest",
      "tab": "festivals"
    },
    {
      "id": "921ae011d1",
      "title": "Bradley Cooper’s ‘Maestro’ Set As Spotlight Gala At New York Film Festival",
      "link": "https://deadline.com/2023/08/bradley-cooper-maestro-spotlight-gala-new-york-film-festival-1235520298/",
      "pubDate": "Wed, 16 Aug 2023 15:00:00 +0000",
      "source": "Deadline Festivals",
      "sourceId": "deadline_fest",
      "tab": "festivals"
    },
    {
      "id": "50067225e3",
      "title": "Zoe Saldaña, Garrett Hedlund & Adria Arjona Thriller ‘The Absence Of Eden’ Sets Taormina World Premiere",
      "link": "https://deadline.com/2023/06/the-absence-of-eden-taormina-world-premiere-1235420543/",
      "pubDate": "Tue, 20 Jun 2023 11:27:37 +0000",
      "source": "Deadline Festivals",
      "sourceId": "deadline_fest",
      "tab": "festivals"
    },
    {
      "id": "8c02da2667",
      "title": "Berlin Jury Announced; Includes Golshifteh Farahani, Johnnie To & ‘12 Years A Slave’, ‘Babylon’, ‘She Said’ Casting Director  Francine Maisler",
      "link": "https://deadline.com/2023/02/berlin-jury-2023-golshifteh-farahani-amp-johnnie-to-kristen-stewart-1235246398/",
      "pubDate": "Wed, 01 Feb 2023 13:20:46 +0000",
      "source": "Deadline Festivals",
      "sourceId": "deadline_fest",
      "tab": "festivals"
    },
    {
      "id": "4e8a85a232",
      "title": "New York Film Festival Promotes Veteran Operations Exec Matt Bolish To Managing Director, Reveals Dates For This Fall’s 61st Edition",
      "link": "https://deadline.com/2023/01/new-york-film-festival-promotes-veteran-operations-exec-matt-bolish-managing-director-1235225088/",
      "pubDate": "Wed, 18 Jan 2023 18:00:00 +0000",
      "source": "Deadline Festivals",
      "sourceId": "deadline_fest",
      "tab": "festivals"
    },
    {
      "id": "db398169df",
      "title": "How Major Film Festivals Launched This Year’s Biggest Oscar Contenders, from ‘Dune’ to ‘The Power of the Dog’",
      "link": "https://www.indiewire.com/awards/industry/how-film-festivals-launched-2022-oscar-nominees-1234701288/",
      "pubDate": "Tue, 22 Feb 2022 20:30:51 +0000",
      "source": "IndieWire Festivals",
      "sourceId": "indiewire_fest",
      "tab": "festivals"
    },
    {
      "id": "4afc0c304e",
      "title": "‘Fortnite’ Is the First Video Game to Host a Film Festival, with a Potential Audience of 350 Million",
      "link": "https://www.indiewire.com/features/commentary/fortnite-video-game-film-festival-1234617751/",
      "pubDate": "Sat, 20 Feb 2021 15:00:59 +0000",
      "source": "IndieWire Festivals",
      "sourceId": "indiewire_fest",
      "tab": "festivals"
    },
    {
      "id": "abdd766f9f",
      "title": "Every Film Festival and Market Still Happening in 2020, in Person and Online",
      "link": "https://www.indiewire.com/features/general/film-festival-market-2020-in-person-online-1202232252/",
      "pubDate": "Mon, 30 Nov 2020 17:45:45 +0000",
      "source": "IndieWire Festivals",
      "sourceId": "indiewire_fest",
      "tab": "festivals"
    },
    {
      "id": "2b93bcca92",
      "title": "Film Festivals Aren’t Just Surviving Online, They’re Creating a Better Future",
      "link": "https://www.indiewire.com/features/general/film-festivals-online-future-1202231417/",
      "pubDate": "Sat, 16 May 2020 14:00:36 +0000",
      "source": "IndieWire Festivals",
      "sourceId": "indiewire_fest",
      "tab": "festivals"
    },
    {
      "id": "e03dfb163e",
      "title": "Locarno Film Festival Cancels 2020 Edition and Won’t Go Virtual",
      "link": "https://www.indiewire.com/features/general/locarno-film-festival-canceled-1202228108/",
      "pubDate": "Wed, 29 Apr 2020 14:40:53 +0000",
      "source": "IndieWire Festivals",
      "sourceId": "indiewire_fest",
      "tab": "festivals"
    },
    {
      "id": "af1676173f",
      "title": "Cannes Says June Festival ‘No Longer an Option’ While Exploring Contingency",
      "link": "https://www.indiewire.com/features/general/cannes-film-festival-no-longer-option-contingency-1202223760/",
      "pubDate": "Tue, 14 Apr 2020 16:23:11 +0000",
      "source": "IndieWire Festivals",
      "sourceId": "indiewire_fest",
      "tab": "festivals"
    },
    {
      "id": "01a0562102",
      "title": "Cannes Marches On: Inside the Crisis Facing the World’s Most Prominent Festival",
      "link": "https://www.indiewire.com/features/general/thierry-fremaux-cannes-canceled-1202223647/",
      "pubDate": "Wed, 08 Apr 2020 18:30:21 +0000",
      "source": "IndieWire Festivals",
      "sourceId": "indiewire_fest",
      "tab": "festivals"
    },
    {
      "id": "2005444e0a",
      "title": "The Unbridgeable Divide: How True/False’s Celebrated Partnership With an Evangelical Church Imploded",
      "link": "https://www.indiewire.com/features/general/true-false-film-fest-the-crossing-evangelical-church-partnership-1202215737/",
      "pubDate": "Mon, 09 Mar 2020 15:00:46 +0000",
      "source": "IndieWire Festivals",
      "sourceId": "indiewire_fest",
      "tab": "festivals"
    },
    {
      "id": "24479fa838",
      "title": "New York Film Festival’s New Director Is IndieWire Co-Founder Eugene Hernandez",
      "link": "https://www.indiewire.com/features/general/eugene-hernandez-new-york-film-festival-director-1202212057/",
      "pubDate": "Wed, 19 Feb 2020 14:00:18 +0000",
      "source": "IndieWire Festivals",
      "sourceId": "indiewire_fest",
      "tab": "festivals"
    },
    {
      "id": "a0e8dbf8c8",
      "title": "Don’t Expect Martin Scorsese’s ‘The Irishman’ to Screen at Fall Film Festivals",
      "link": "https://www.indiewire.com/awards/industry/martin-scorseses-the-irishman-netflix-fall-film-festivals-1202149005/",
      "pubDate": "Tue, 25 Jun 2019 17:50:12 +0000",
      "source": "IndieWire Festivals",
      "sourceId": "indiewire_fest",
      "tab": "festivals"
    },
    {
      "id": "0e093289ef",
      "title": "James Gray: Film Festivals Are Problematic Because Directors and Critics Are Bad at Judging Films",
      "link": "https://www.indiewire.com/features/general/james-gray-problem-film-festivals-directors-critics-bad-judging-films-1202026572/",
      "pubDate": "Sat, 08 Dec 2018 20:30:28 +0000",
      "source": "IndieWire Festivals",
      "sourceId": "indiewire_fest",
      "tab": "festivals"
    }
  ]
}